LICENSE
MANIFEST.in
README.md
setup.cfg
setup.py
pyexec/__init__.py
pyexec/pyexec.py
sphinxcontrib_pyexec.egg-info/PKG-INFO
sphinxcontrib_pyexec.egg-info/SOURCES.txt
sphinxcontrib_pyexec.egg-info/dependency_links.txt
sphinxcontrib_pyexec.egg-info/requires.txt
sphinxcontrib_pyexec.egg-info/top_level.txt
tests/__init__.py
tests/test_docs.py