Metadata-Version: 1.1
Name: sphinxcontrib-pyexec
Version: 0.0.4
Summary: sphinxcontrib-pyexec
Home-page: https://github.com/3ptscience/sphinxcontrib-pyexec
Author: Lindsey Heagy
Author-email: lindsey@3ptscience.com
License: MIT
Download-URL: https://github.com/3ptscience/sphinxcontrib-pyexec
Keywords: sphinx documentation python execute
Platform: Windows
Platform: Linux
Platform: Solaris
Platform: Mac OS-X
Platform: Unix
Classifier: Development Status :: 3 - Alpha
Classifier: Intended Audience :: Developers
Classifier: License :: OSI Approved :: MIT License
Classifier: Programming Language :: Python
Classifier: Programming Language :: Python :: 2.7
Classifier: Programming Language :: Python :: 3.3
Classifier: Programming Language :: Python :: 3.4
Classifier: Programming Language :: Python :: 3.5
Classifier: Operating System :: Microsoft :: Windows
Classifier: Operating System :: POSIX
Classifier: Operating System :: Unix
Classifier: Operating System :: MacOS
Classifier: Natural Language :: English
